{
    "status": true,
    "message": "调用成功",
    "data": {
        "pageNo": 1,
        "pageSize": 4,
        "totalRecord": 2281,
        "totalPage": 71,
        "countKey": "1",
        "results": [
            {
                "id": "201612081807133481101910000062",
                "detail": "称手机被盗。",
                "aymc": "扒窃",
                "sj": "2017-02-08 18:07:13",
                "sfdz": "观音桥世纪金街"
            },
            {
                "id": "201612081715334951101610000037",
                "detail": "称苹果手机被盗。",
                "aymc": "侵犯财产案",
                "sj": "2017-02-08 17:15:33",
                "sfdz": "鱼洞永辉超市"
            },
            {
                "id": "201612081700302621101610000003",
                "detail": "称手机被盗。",
                "aymc": "扒窃",
                "sj": "2017-02-08 17:00:39",
                "sfdz": "北城天街乡村基"
            },
            {
                "id": "201612081653191252510001677125",
                "detail": "2016年11月29日上午9时左右，祝子凤将钱包和手机放在北碚区月亮田川渝纸包鱼店里便择菜去了，当天10点左右祝子凤发现钱包和手机被盗了。钱包内有祝子凤的身份证和现金2380元和一个黄金戒指。手机是一部红色翻盖的老年机。共损失4080元。",
                "aymc": "其他盗窃",
                "sj": "2017-02-08 16:48:22",
                "sfdz": "北碚区月亮田川渝纸包鱼"
            }
        ],
        "params": {
            "beginTime": 1485944920995,
            "word": "%手机被盗%",
            "endTime": 1486549720995
        }
    }
}
