{
    "code": 1,
    "msg": "success",
    "result": [
        {
            "name": "全部",
            "value": 1379,
            "type": "0000"
        },
        {
            "name": "八类",
            "value": 131,
            "type": "1000",
            "child": [
                {
                    "name": "抢劫",
                    "value": 53,
                    "type": "1003"
                },
                {
                    "name": "故意伤害",
                    "value": 33,
                    "type": "1002"
                },
                {
                    "name": "故意杀人",
                    "value": 19,
                    "type": "1001"
                },
                {
                    "name": "强奸",
                    "value": 16,
                    "type": "1004"
                },
                {
                    "name": "绑架",
                    "value": 7,
                    "type": "1005"
                },
                {
                    "name": "纵火",
                    "value": 3,
                    "type": "1007"
                },
                {
                    "name": "爆炸",
                    "value": 0,
                    "type": "1006"
                },
                {
                    "name": "投毒",
                    "value": 0,
                    "type": "1008"
                }
            ]
        },
        {
            "name": "侵财",
            "value": 396,
            "type": "2000",
            "child": [
                {
                    "name": "入室盗窃",
                    "value": 182,
                    "type": "2001"
                },
                {
                    "name": "电信诈骗",
                    "value": 74,
                    "type": "2002"
                },
                {
                    "name": "盗窃摩托车",
                    "value": 65,
                    "type": "2003"
                },
                {
                    "name": "扒窃",
                    "value": 43,
                    "type": "2005"
                },
                {
                    "name": "盗窃车内物品",
                    "value": 32,
                    "type": "2004"
                }
            ]
        },
        {
            "name": "毒品",
            "value": 118,
            "type": "3000",
            "child": [
                {
                    "name": "毒品-贩卖毒品",
                    "value": 99,
                    "type": "caseClass_86"
                },
                {
                    "name": "毒品-运输毒品",
                    "value": 9,
                    "type": "caseClass_87"
                },
                {
                    "name": "毒品-制造毒品",
                    "value": 4,
                    "type": "caseClass_85"
                },
                {
                    "name": "毒品-持有毒品",
                    "value": 3,
                    "type": "caseClass_89"
                },
                {
                    "name": "毒品-其他",
                    "value": 3,
                    "type": "caseClass_91"
                },
                {
                    "name": "毒品-走私毒品",
                    "value": 0,
                    "type": "caseClass_88"
                }
            ]
        },
        {
            "name": "经济",
            "value": 127,
            "type": "4000",
            "child": [
                {
                    "name": "经济-其他",
                    "value": 24,
                    "type": "caseClass_84"
                },
                {
                    "name": "经济-非法经营",
                    "value": 20,
                    "type": "caseClass_68"
                },
                {
                    "name": "经济-贪污贿赂",
                    "value": 15,
                    "type": "caseClass_66"
                },
                {
                    "name": "经济-合同诈骗",
                    "value": 15,
                    "type": "caseClass_74"
                },
                {
                    "name": "经济-生产、销售伪劣产品",
                    "value": 12,
                    "type": "caseClass_72"
                },
                {
                    "name": "经济-销售假冒注册商标的商品",
                    "value": 7,
                    "type": "caseClass_82"
                },
                {
                    "name": "经济-挪用资金",
                    "value": 5,
                    "type": "caseClass_81"
                },
                {
                    "name": "经济-职务侵占",
                    "value": 5,
                    "type": "caseClass_75"
                },
                {
                    "name": "经济-生产、销售有毒、有害食品",
                    "value": 4,
                    "type": "caseClass_80"
                },
                {
                    "name": "经济-传销",
                    "value": 4,
                    "type": "caseClass_67"
                },
                {
                    "name": "经济-非法出售增值税专用发票",
                    "value": 4,
                    "type": "caseClass_77"
                },
                {
                    "name": "经济-走私",
                    "value": 4,
                    "type": "caseClass_83"
                },
                {
                    "name": "经济-集资诈骗",
                    "value": 3,
                    "type": "caseClass_71"
                },
                {
                    "name": "经济-出售、购买、运输假币",
                    "value": 2,
                    "type": "caseClass_70"
                },
                {
                    "name": "经济-串通投标",
                    "value": 2,
                    "type": "caseClass_73"
                },
                {
                    "name": "经济-洗钱",
                    "value": 1,
                    "type": "caseClass_78"
                },
                {
                    "name": "经济-生产、销售不符合卫生标准的食品",
                    "value": 0,
                    "type": "caseClass_76"
                },
                {
                    "name": "经济案件.破坏金融管理秩序",
                    "value": 0,
                    "type": "TC_cs_Economy$$TC_cse_PHJRGLZX"
                },
                {
                    "name": "经济案件.贪污",
                    "value": 0,
                    "type": "TC_cs_Economy$$TC_cse_TanWu"
                },
                {
                    "name": "经济案件.受贿",
                    "value": 0,
                    "type": "TC_cs_Economy$$TC_cse_ShouHui"
                },
                {
                    "name": "经济案件.非法经营",
                    "value": 0,
                    "type": "TC_cs_Economy$$TC_cse_FFJY"
                },
                {
                    "name": "经济-利用职权实施侵犯公民人身权利",
                    "value": 0,
                    "type": "caseClass_79"
                },
                {
                    "name": "经济案件.挪用公款",
                    "value": 0,
                    "type": "TC_cs_Economy$$TC_cse_NYGK"
                },
                {
                    "name": "经济案件",
                    "value": 0,
                    "type": "TC_cs_Economy"
                },
                {
                    "name": "经济案件.破坏市场经济秩序",
                    "value": 0,
                    "type": "TC_cs_Economy$$TC_cse_BHSCJJZX"
                },
                {
                    "name": "经济案件.金融诈骗",
                    "value": 0,
                    "type": "TC_cs_Economy$$TC_cse_JRZP"
                },
                {
                    "name": "经济案件.扰乱市场秩序",
                    "value": 0,
                    "type": "TC_cs_Economy$$TC_cse_RLSCZX"
                },
                {
                    "name": "经济案件.制贩假币",
                    "value": 0,
                    "type": "TC_cs_Economy$$TC_cse_ZFJB"
                },
                {
                    "name": "经济案件.合同诈骗",
                    "value": 0,
                    "type": "TC_cs_Economy$$TC_cse_HTZP"
                },
                {
                    "name": "经济案件.行贿",
                    "value": 0,
                    "type": "TC_cs_Economy$$TC_cse_XingHui"
                },
                {
                    "name": "经济案件.侵犯知识产权",
                    "value": 0,
                    "type": "TC_cs_Economy$$TC_cse_QFZSCQ"
                },
                {
                    "name": "经济案件.妨害对公司企业的",
                    "value": 0,
                    "type": "TC_cs_Economy$$TC_cse_FHGSQY"
                },
                {
                    "name": "经济案件.危害税收征管",
                    "value": 0,
                    "type": "TC_cs_Economy$$TC_cse_WHSSZG"
                },
                {
                    "name": "经济案件.生产销售伪劣商品",
                    "value": 0,
                    "type": "TC_cs_Economy$$TC_cse_SCXSWLSP"
                },
                {
                    "name": "经济案件.贪污贿赂",
                    "value": 0,
                    "type": "TC_cs_Economy$$TC_cse_TWHL"
                }
            ]
        },
        {
            "name": "国保",
            "value": 0,
            "type": "5000"
        },
        {
            "name": "其他",
            "value": 607,
            "type": "6000"
        }
    ]
}